arth/__init__.py
arth/addition.py
arth/multiplication.py
arth/subtraction.py
non_arth/__init__.py
non_arth/determinant.py
non_arth/transpose.py
MatMan-0.0.1.dist-info/METADATA
MatMan-0.0.1.dist-info/WHEEL
MatMan-0.0.1.dist-info/top_level.txt
MatMan-0.0.1.dist-info/RECORD
