Metadata-Version: 2.1
Name: MatMan
Version: 0.0.1
Summary: MatOps has 2 pakages that perform arithmetic (Maltiplication, Addition, Subtraction) and non-arithmetic (Transpose, 		Determinent) operation on matrices
Author: MSDSF22M020_Taha
Author-email: taha@gmail.com
Classifier: Programming Language :: Python :: 3
Classifier: License :: OSI Approved :: MIT License
Classifier: Operating System :: OS Independent
